civilTools/RSN139_TABAS_DAY-L1.AT2
civilTools/__init__.py
civilTools/about.ui
civilTools/checkupdate.py
civilTools/civiltools.py
civilTools/guiSaveRestore.py
civilTools/main_form.ui
civilTools/resource_rc.py
civilTools/versions.py
civilTools/applications/__init__.py
civilTools/applications/cfactor/.directory
civilTools/applications/cfactor/MainWindow.py
civilTools/applications/cfactor/__init__.py
civilTools/applications/cfactor/export.py
civilTools/applications/cfactor/guiSaveRestore.py
civilTools/applications/cfactor/models.py
civilTools/applications/cfactor/building/RuTable.py
civilTools/applications/cfactor/building/__init__.py
civilTools/applications/cfactor/building/build.py
civilTools/applications/cfactor/building/soil.py
civilTools/applications/cfactor/db/__init__.py
civilTools/applications/cfactor/db/ostanha.py
civilTools/applications/cfactor/exporter/__init__.py
civilTools/applications/cfactor/exporter/config.json
civilTools/applications/cfactor/exporter/config.py
civilTools/applications/cfactor/exporter/export_to_word.py
civilTools/applications/cfactor/exporter/exporttoetabsdlg1.py
civilTools/applications/cfactor/exporter/template.docx
civilTools/applications/cfactor/images/.directory
civilTools/applications/cfactor/images/cfactor.png
civilTools/applications/cfactor/images/etabs2015.jpg
civilTools/applications/cfactor/images/etabs2016.jpg
civilTools/applications/cfactor/images/excel_exports.png
civilTools/applications/cfactor/images/export_etabs.png
civilTools/applications/cfactor/images/file_extension_html.png
civilTools/applications/cfactor/images/file_extension_pdf.png
civilTools/applications/cfactor/images/file_extension_png.png
civilTools/applications/cfactor/images/report_word.png
civilTools/applications/cfactor/images/save_as.png
civilTools/applications/cfactor/plots/__init__.py
civilTools/applications/cfactor/plots/plotB.py
civilTools/applications/cfactor/tests/2800R4.xls
civilTools/applications/cfactor/tests/__init__.py
civiltools-1.5.2.dist-info/AUTHORS.rst
civiltools-1.5.2.dist-info/LICENSE
civiltools-1.5.2.dist-info/METADATA
civiltools-1.5.2.dist-info/WHEEL
civiltools-1.5.2.dist-info/top_level.txt
civiltools-1.5.2.dist-info/RECORD
