Metadata-Version: 2.1
Name: civiltools
Version: 1.5.2
Summary: A series of tools for civil engineers.
Home-page: https://github.com/ebrahimraeyat/civiltools
Author: Raeyat Ebrahim
Author-email: ebe79442114@yahoo.com
License: GPL-3.0
Keywords: civiltools
Platform: UNKNOWN
Classifier: Development Status :: 2 - Pre-Alpha
Classifier: Intended Audience :: Developers
Classifier: License :: OSI Approved :: GNU General Public License (GPL)
Classifier: Natural Language :: Persian
Classifier: Programming Language :: Python :: 3
Classifier: Programming Language :: Python :: 3.3
Classifier: Programming Language :: Python :: 3.4
Classifier: Programming Language :: Python :: 3.5
Classifier: Programming Language :: Python :: 3.6
Requires-Dist: matplotlib (>=2.0.0)
Requires-Dist: numpy (>=1.12.1)
Requires-Dist: pandas (>=0.19.2)
Requires-Dist: PyQt5 (>=5.8.1)
Requires-Dist: pyqtgraph (>=0.10.0)
Requires-Dist: python-docx (>=0.8.7)
